cpf3d/__init__.py
cpf3d/frame.py
cpf3d/point.py
cpf3d/point_frames.py
cpf3d-1.0.0.dist-info/LICENSE.txt
cpf3d-1.0.0.dist-info/METADATA
cpf3d-1.0.0.dist-info/WHEEL
cpf3d-1.0.0.dist-info/top_level.txt
cpf3d-1.0.0.dist-info/RECORD
