Metadata-Version: 2.1
Name: cpf3d
Version: 1.0.0
Summary: A package for reading and writing 3cpf files.
Home-page: https://github.com/ruelalarcon/cpf3d
Author: Ruel Nathaniel Alarcon
Author-email: ruelnalarcon@gmail.com
License: MIT
Project-URL: Repository, https://github.com/ruelalarcon/cpf3d
Keywords: 3cpf,point,cloud,frames
Classifier: License :: OSI Approved :: MIT License
Classifier: Programming Language :: Python :: 3
Classifier: Programming Language :: Python :: 3.8
Classifier: Programming Language :: Python :: 3.9
Classifier: Programming Language :: Python :: 3.10
Classifier: Programming Language :: Python :: 3.11
Classifier: Programming Language :: Python :: 3.12
Requires-Python: >=3.8
License-File: LICENSE.txt
Requires-Dist: numpy
Provides-Extra: dev
Requires-Dist: pytest ; extra == 'dev'
